binance_sdk_mining/__init__.py
binance_sdk_mining/metadata.py
binance_sdk_mining/mining.py
binance_sdk_mining/rest_api/__init__.py
binance_sdk_mining/rest_api/api/__init__.py
binance_sdk_mining/rest_api/api/mining_api.py
binance_sdk_mining/rest_api/models/__init__.py
binance_sdk_mining/rest_api/models/account_list_response.py
binance_sdk_mining/rest_api/models/account_list_response_data_inner.py
binance_sdk_mining/rest_api/models/account_list_response_data_inner_list_inner.py
binance_sdk_mining/rest_api/models/acquiring_algorithm_response.py
binance_sdk_mining/rest_api/models/acquiring_algorithm_response_data_inner.py
binance_sdk_mining/rest_api/models/acquiring_coinname_response.py
binance_sdk_mining/rest_api/models/acquiring_coinname_response_data_inner.py
binance_sdk_mining/rest_api/models/cancel_hashrate_resale_configuration_response.py
binance_sdk_mining/rest_api/models/earnings_list_response.py
binance_sdk_mining/rest_api/models/earnings_list_response_data.py
binance_sdk_mining/rest_api/models/earnings_list_response_data_account_profits_inner.py
binance_sdk_mining/rest_api/models/enums.py
binance_sdk_mining/rest_api/models/extra_bonus_list_response.py
binance_sdk_mining/rest_api/models/extra_bonus_list_response_data.py
binance_sdk_mining/rest_api/models/extra_bonus_list_response_data_other_profits_inner.py
binance_sdk_mining/rest_api/models/hashrate_resale_detail_response.py
binance_sdk_mining/rest_api/models/hashrate_resale_detail_response_data.py
binance_sdk_mining/rest_api/models/hashrate_resale_detail_response_data_profit_transfer_details_inner.py
binance_sdk_mining/rest_api/models/hashrate_resale_list_response.py
binance_sdk_mining/rest_api/models/hashrate_resale_list_response_data.py
binance_sdk_mining/rest_api/models/hashrate_resale_list_response_data_config_details_inner.py
binance_sdk_mining/rest_api/models/hashrate_resale_request_response.py
binance_sdk_mining/rest_api/models/mining_account_earning_response.py
binance_sdk_mining-3.0.0.dist-info/METADATA
binance_sdk_mining-3.0.0.dist-info/WHEEL
binance_sdk_mining-3.0.0.dist-info/licenses/LICENCE
binance_sdk_mining-3.0.0.dist-info/RECORD
